parsy/__init__.py
parsy/version.py
parsy-2.0.dist-info/LICENSE
parsy-2.0.dist-info/METADATA
parsy-2.0.dist-info/WHEEL
parsy-2.0.dist-info/top_level.txt
parsy-2.0.dist-info/RECORD
