Metadata-Version: 2.1
Name: parsy
Version: 2.0
Summary: easy-to-use parser combinators, for parsing in pure Python
Home-page: https://github.com/python-parsy/parsy
Author: Jeanine Adkisson
Author-email: jneen@jneen.net
Maintainer: Luke Plant
Maintainer-email: L.Plant.98@cantab.net
License: MIT
Keywords: parser parsers parsing monad combinators
Platform: UNKNOWN
Classifier: Development Status :: 5 - Production/Stable
Classifier: Intended Audience :: Developers
Classifier: Topic :: Software Development :: Compilers
Classifier: Topic :: Software Development :: Interpreters
Classifier: Topic :: Text Processing
Classifier: License :: OSI Approved :: MIT License
Classifier: Programming Language :: Python :: 3
Classifier: Programming Language :: Python :: 3.6
Classifier: Programming Language :: Python :: 3.7
Classifier: Programming Language :: Python :: 3.8
Classifier: Programming Language :: Python :: 3.9
Classifier: Programming Language :: Python :: 3.10
Requires-Python: >=3.6
License-File: LICENSE
